furry/__init__.py
furry/main.py
kurzaj/__init__.py
kurzaj/capybara.jpg
kurzaj/main.py
kurzajutils/__init__.py
kurzajutils/main.py
kurzaj-0.16.0.dist-info/METADATA
kurzaj-0.16.0.dist-info/WHEEL
kurzaj-0.16.0.dist-info/top_level.txt
kurzaj-0.16.0.dist-info/RECORD
