Metadata-Version: 2.4
Name: kurzaj
Version: 0.16.0
Summary: furry po edition
Home-page: https://example.com/
Author: meow
Requires-Python: >=3.6
Requires-Dist: Pillow
Dynamic: author
Dynamic: description
Dynamic: description-content-type
Dynamic: home-page
Dynamic: requires-dist
Dynamic: requires-python
Dynamic: summary
